{
  "Base Set": "Set de Base",
  "Jungle": "Jungle",
  "Fossil": "Fossile",
  "Team Rocket": "Équipe Rocket",
  "Gym Heroes": "Héros de la Salle",
  "Gym Challenge": "Défi de la Salle",
  "Neo Genesis": "Néo Genesis",
  "Neo Discovery": "Néo Découverte",
  "Neo Revelation": "Néo Révélation",
  "Neo Destiny": "Néo Destinée",
  "Expedition Base Set": "Set de Base Expédition",
  "Aquapolis": "Aquapolis",
  "Skyridge": "Skyridge",
  "EX Ruby & Sapphire": "EX Rubis & Saphir",
  "EX Sandstorm": "EX Tempête de Sable",
  "EX Dragon": "EX Dragon",
  "EX Team Magma vs Team Aqua": "EX Équipe Magma vs Équipe Aqua",
  "EX Hidden Legends": "EX Légendes Cachées",
  "EX FireRed & LeafGreen": "EX Rouge Feu & Vert Feuille",
  "EX Team Rocket Returns": "EX Retour de l'Équipe Rocket",
  "EX Deoxys": "EX Deoxys",
  "EX Emerald": "EX Émeraude",
  "EX Unseen Forces": "EX Forces Invisibles",
  "EX Delta Species": "EX Espèces Delta",
  "EX Legend Maker": "EX Créateur de Légendes",
  "EX Holon Phantoms": "EX Fantômes Holon",
  "EX Crystal Guardians": "EX Gardiens de Cristal",
  "EX Dragon Frontiers": "EX Frontières Dragon",
  "EX Power Keepers": "EX Gardiens du Pouvoir",
  "Diamond & Pearl": "Diamant & Perle",
  "Mysterious Treasures": "Trésors Mystérieux",
  "Secret Wonders": "Merveilles Secrètes",
  "Great Encounters": "Grandes Rencontres",
  "Majestic Dawn": "Aube Majestueuse",
  "Legends Awakened": "Légendes Réveillées",
  "Stormfront": "Front de Tempête",
  "Platinum": "Platine",
  "Rising Rivals": "Rivaux Montants",
  "Supreme Victors": "Vainqueurs Suprêmes",
  "Arceus": "Arceus",
  "HeartGold & SoulSilver": "Cœur d'Or & Âme d'Argent",
  "HS—Unleashed": "HS—Déchaîné",
  "HS—Undaunted": "HS—Intrépide",
  "HS—Triumphant": "HS—Triomphant",
  "Call of Legends": "Appel des Légendes",
  "Black & White": "Noir & Blanc",
  "Emerging Powers": "Pouvoirs Émergents",
  "Noble Victories": "Victoires Nobles",
  "Next Destinies": "Prochaines Destinées",
  "Dark Explorers": "Explorateurs des Ténèbres",
  "Dragons Exalted": "Dragons Exaltés",
  "Boundaries Crossed": "Frontières Traversées",
  "Plasma Storm": "Tempête Plasma",
  "Plasma Freeze": "Gel Plasma",
  "Plasma Blast": "Explosion Plasma",
  "Legendary Treasures": "Trésors Légendaires",
  "XY": "XY",
  "Furious Fists": "Poings Furieux",
  "Phantom Forces": "Forces Fantômes",
  "Primal Clash": "Choc Primal",
  "Roaring Skies": "Cieux Rugissants",
  "Ancient Origins": "Origines Anciennes",
  "BREAKthrough": "Perceé",
  "BREAKpoint": "Point de Rupture",
  "Fates Collide": "Destins qui s'Entrecroisent",
  "Steam Siege": "Siège de Vapeur",
  "Evolutions": "Évolutions",
  "Sun & Moon": "Soleil & Lune",
  "Guardians Rising": "Gardiens Montants",
  "Burning Shadows": "Ombres Ardentes",
  "Shining Legends": "Légendes Brillantes",
  "Crimson Invasion": "Invasion Cramoisie",
  "Ultra Prism": "Prisme Ultra",
  "Forbidden Light": "Lumière Interdite",
  "Celestial Storm": "Tempête Céleste",
  "Dragon Majesty": "Majesté Dragon",
  "Lost Thunder": "Tonnerre Perdu",
  "Team Up": "Équipe Unie",
  "Unbroken Bonds": "Liens Inébranlables",
  "Unified Minds": "Esprits Unis",
  "Cosmic Eclipse": "Éclipse Cosmique",
  "Sword & Shield": "Épée & Bouclier",
  "Rebel Clash": "Choc Rebelle",
  "Darkness Ablaze": "Ténèbres Ardentes",
  "Champion's Path": "Voie du Champion",
  "Vivid Voltage": "Voltage Vif",
  "Shining Fates": "Destins Brillants",
  "Battle Styles": "Styles de Combat",
  "Chilling Reign": "Règne Glacial",
  "Evolving Skies": "Cieux Évoluants",
  "Fusion Strike": "Frappe Fusion",
  "Brilliant Stars": "Étoiles Brillantes",
  "Astral Radiance": "Radiance Astrale",
  "Lost Origin": "Origine Perdue",
  "Silver Tempest": "Tempête d'Argent",
  "Crown Zenith": "Zénith Couronné",
  "Scarlet & Violet": "Écarlate & Violet",
  "Paldea Evolved": "Paldea Évolué"
}
